counter.v
//加算演算子による4ビット・カウンタ
module counter( ck, res, q );
input		ck, res;
output	[3:0]	q;
reg	[3:0]	q;

always @( posedge ck or posedge res ) begin
	if ( res == 1'b1 ) q  <= 4'h0;
	else q <= q + 4'h1;
end

endmodule

counter_tp.v
//1ユニットを1psに設定
`timescale 1ps/1ps

module counter_tp;
reg		ck, res; //入力をreg宣言
wire	[3:0]	q;	 //出力をwire宣言

parameter STEP = 100000; //1周期　100ns

// テスト対象呼び出し
counter counter( ck, res, q );

//　クロック作成
always begin
	ck = 0; #(STEP/2);
	ck = 1; #(STEP/2);
end
//　テスト入力
initial begin
		res = 0;
	#STEP	res = 1;
	#STEP	res = 0;
	#(STEP*20) $finish;
end

//表示
initial begin 
	$monitor( $stime," ck=%b res=%b q=%h", ck, res, q);
	$dumpfile("counter_tp.vcd");
	$dumpvars( 0,counter_tp );
end

endmodule

counter_tp.vcd
$date
	Thu Oct 10 10:36:41 2019
$end
$version
	Icarus Verilog
$end
$timescale
	1ps
$end
$scope module counter_tp $end
$var wire 4 ! q [3:0] $end
$var reg 1 " ck $end
$var reg 1 # res $end
$scope module counter $end
$var wire 1 " ck $end
$var wire 1 # res $end
$var reg 4 $ q [3:0] $end
$upscope $end
$upscope $end
$enddefinitions $end
#0
$dumpvars
bx $
0#
0"
bx !
$end
#50000
1"
#100000
b0 !
b0 $
0"
1#
#150000
1"
#200000
0"
0#
#250000
b1 !
b1 $
1"
#300000
0"
#350000
b10 !
b10 $
1"
#400000
0"
#450000
b11 !
b11 $
1"
#500000
0"
#550000
b100 !
b100 $
1"
#600000
0"
#650000
b101 !
b101 $
1"
#700000
0"
#750000
b110 !
b110 $
1"
#800000
0"
#850000
b111 !
b111 $
1"
#900000
0"
#950000
b1000 !
b1000 $
1"
#1000000
0"
#1050000
b1001 !
b1001 $
1"
#1100000
0"
#1150000
b1010 !
b1010 $
1"
#1200000
0"
#1250000
b1011 !
b1011 $
1"
#1300000
0"
#1350000
b1100 !
b1100 $
1"
#1400000
0"
#1450000
b1101 !
b1101 $
1"
#1500000
0"
#1550000
b1110 !
b1110 $
1"
#1600000
0"
#1650000
b1111 !
b1111 $
1"
#1700000
0"
#1750000
b0 !
b0 $
1"
#1800000
0"
#1850000
b1 !
b1 $
1"
#1900000
0"
#1950000
b10 !
b10 $
1"
#2000000
0"
#2050000
b11 !
b11 $
1"
#2100000
0"
#2150000
b100 !
b100 $
1"
